dptoie/__init__.py
dptoie/extraction.py
dptoie/main.py
dptoie-0.1.6.dist-info/METADATA
dptoie-0.1.6.dist-info/WHEEL
dptoie-0.1.6.dist-info/RECORD
