Metadata-Version: 2.4
Name: dptoie
Version: 0.1.6
Summary: DPToie-Python is an Open Information Extractor for Portuguese language that employs Dependence Parser and Part of Speech Tagger models with Stanford CoreNLP.
Author: André Walker
Author-email: andre.walker@ufba.br
Requires-Python: >=3.12,<3.14
Classifier: Programming Language :: Python :: 3
Classifier: Programming Language :: Python :: 3.12
Classifier: Programming Language :: Python :: 3.13
Requires-Dist: formas-spacy-stanza (>=1.0.5,<2.0.0)
Requires-Dist: spacy (==3.8.7)
Requires-Dist: spacy-conll (>=4.0.1,<5.0.0)
Requires-Dist: stanza (==1.10.1)
Requires-Dist: torch (==2.7.1)
Requires-Dist: tqdm (>=4.67.1,<5.0.0)
